LICENSE
MANIFEST.in
README
README.md
setup.py
Flask_Table.egg-info/PKG-INFO
Flask_Table.egg-info/SOURCES.txt
Flask_Table.egg-info/dependency_links.txt
Flask_Table.egg-info/requires.txt
Flask_Table.egg-info/top_level.txt
flask_table/__init__.py
flask_table/columns.py
flask_table/compat.py
flask_table/html.py
flask_table/table.py