Metadata-Version: 1.1
Name: Flask-Table
Version: 0.5.0
Summary: HTML tables for use with the Flask micro-framework
Home-page: https://github.com/plumdog/flask_table
Author: Andrew Plummer
Author-email: plummer574@gmail.com
License: UNKNOWN
Platform: UNKNOWN
Classifier: Development Status :: 3 - Alpha
Classifier: Programming Language :: Python
Classifier: Programming Language :: Python :: 2
Classifier: Programming Language :: Python :: 2.7
Classifier: Programming Language :: Python :: 3
Classifier: Programming Language :: Python :: 3.3
Classifier: Programming Language :: Python :: 3.4
Classifier: Operating System :: OS Independent
Classifier: Framework :: Flask
